plover_casecat/__init__.py
plover_casecat/dict.py
plover_casecat/translation.py
plover_casecat-1.0.0.dist-info/licenses/LICENSE
plover_casecat-1.0.0.dist-info/METADATA
plover_casecat-1.0.0.dist-info/WHEEL
plover_casecat-1.0.0.dist-info/entry_points.txt
plover_casecat-1.0.0.dist-info/top_level.txt
plover_casecat-1.0.0.dist-info/RECORD
