Metadata-Version: 2.4
Name: plover-casecat
Version: 1.0.0
Summary: Stenograph Case CATalyst dictionary format plugin for Plover
Author-email: Sammi Ta <sammi@sammdot.ca>
License: MIT License
Project-URL: repository, https://github.com/sammdot/plover-casecat
Project-URL: homepage, https://github.com/sammdot/plover-casecat
Keywords: plover,plover_plugin
Classifier: Programming Language :: Python :: 3.7
Classifier: Programming Language :: Python :: 3.8
Classifier: Programming Language :: Python :: 3.9
Classifier: Programming Language :: Python :: 3.10
Requires-Python: >=3.7
License-File: LICENSE
Requires-Dist: plover>=4.0.0.dev11
Requires-Dist: kaitaistruct>=0.10
Dynamic: license-file
